ouija/__init__.py
ouija/cipher.py
ouija/config.py
ouija/connector.py
ouija/data.py
ouija/entropy.py
ouija/exception.py
ouija/link.py
ouija/log.py
ouija/ouija.py
ouija/proxy.py
ouija/relay.py
ouija/secret.py
ouija/server.py
ouija/telemetry.py
ouija/tuning.py
ouija-1.3.1.dist-info/LICENSE
ouija-1.3.1.dist-info/METADATA
ouija-1.3.1.dist-info/WHEEL
ouija-1.3.1.dist-info/entry_points.txt
ouija-1.3.1.dist-info/top_level.txt
ouija-1.3.1.dist-info/RECORD
