Metadata-Version: 2.1
Name: ouija
Version: 1.3.1
Summary: Python relay/proxy server and library to build reliable encrypted TCP/UDP tunnels with entropy control for TCP traffic
Home-page: https://github.com/neurophant/ouija/
Author: Anton Smolin
Author-email: smolin.anton@gmail.com
License: MIT
Keywords: asyncio http https tcp udp proxy tunnel relay network encrypted cipher security censorship entropy
Classifier: Development Status :: 5 - Production/Stable
Classifier: Environment :: Console
Classifier: Framework :: AsyncIO
Classifier: Intended Audience :: Developers
Classifier: Intended Audience :: Information Technology
Classifier: Intended Audience :: System Administrators
Classifier: Intended Audience :: Other Audience
Classifier: License :: OSI Approved :: MIT License
Classifier: Programming Language :: Python :: 3.11
Classifier: Topic :: Internet :: Proxy Servers
Classifier: Topic :: Internet :: WWW/HTTP :: HTTP Servers
Classifier: Topic :: Security
Classifier: Topic :: Software Development :: Libraries
Classifier: Topic :: System :: Networking
License-File: LICENSE
Requires-Dist: cryptography >=41.0.2
Requires-Dist: pbjson >=1.18.0
Requires-Dist: numpy >=1.25.2
